odoo/addons/account_document_reversal/README.rst
odoo/addons/account_document_reversal/__init__.py
odoo/addons/account_document_reversal/__manifest__.py
odoo/addons/account_document_reversal/i18n/account_document_reversal.pot
odoo/addons/account_document_reversal/i18n/hr.po
odoo/addons/account_document_reversal/i18n/pt.po
odoo/addons/account_document_reversal/models/__init__.py
odoo/addons/account_document_reversal/models/account.py
odoo/addons/account_document_reversal/models/account_bank_statement.py
odoo/addons/account_document_reversal/models/account_document_reversal.py
odoo/addons/account_document_reversal/models/account_invoice.py
odoo/addons/account_document_reversal/models/account_move.py
odoo/addons/account_document_reversal/models/account_payment.py
odoo/addons/account_document_reversal/readme/CONFIGURE.rst
odoo/addons/account_document_reversal/readme/CONTRIBUTORS.rst
odoo/addons/account_document_reversal/readme/DESCRIPTION.rst
odoo/addons/account_document_reversal/readme/USAGE.rst
odoo/addons/account_document_reversal/static/description/icon.png
odoo/addons/account_document_reversal/static/description/index.html
odoo/addons/account_document_reversal/tests/__init__.py
odoo/addons/account_document_reversal/tests/test_invoice_reversal.py
odoo/addons/account_document_reversal/tests/test_payment_reversal.py
odoo/addons/account_document_reversal/views/account_view.xml
odoo/addons/account_document_reversal/wizard/__init__.py
odoo/addons/account_document_reversal/wizard/reverse_account_document.py
odoo/addons/account_document_reversal/wizard/reverse_account_document_wizard.xml
odoo12_addon_account_document_reversal-12.0.1.0.1.dist-info/METADATA
odoo12_addon_account_document_reversal-12.0.1.0.1.dist-info/WHEEL
odoo12_addon_account_document_reversal-12.0.1.0.1.dist-info/top_level.txt
odoo12_addon_account_document_reversal-12.0.1.0.1.dist-info/RECORD
